<!-- $Header: /nfs/slac/g/glast/ground/cvs/xmlGeoDbs/xml/flight/shellDerived.xml,v 1.1 2007/08/15 22:50:16 jrb Exp $ -->

<!-- 

    extra derived constants for testing purposes

-->
<derCategory name="JustTesting" >
  <overview>A place to try out new stuff</overview>
  <const name ="const30" uType="count" value="30.0">
    <notes>A nice number for trig functions</notes>
  </const>
  <const name="sin30" >
    <notes>Should be 0.5</notes>
    <sin>
      <refer refTo="const30" />
    </sin>
  </const>

  <const name="cos30sq" >
    <notes>Should be 0.75</notes>
    <mul>
      <cos>
        <refer refTo="const30" />
      </cos>
      <cos>
        <refer refTo="const30" />
      </cos>
    </mul>
  </const>

  <const name="tan60" >
    <notes>Should be about 1.732</notes>
    <tan>
      <const value="60.0" uType="count" />
    </tan>
  </const>
  
  <const name="roundTrip" >
    <notes>Take asin of sin(30)</notes>
    <asin>
      <refer refTo="sin30" />
    </asin>
  </const>


</derCategory>
