<!-- $Header: /nfs/slac/g/glast/ground/cvs/xmlGeoDbs/xml/flight/flightTKRDimPrim.xml,v 1.8 2007/08/09 15:47:11 jrb Exp $ -->
<primCategory name="TKRDimPrim">
  <overview>Fundamental solid dimensions and offsets within the Tracker.</overview>
<!-- Fundamental Z dimensions in tracker -->
    <prim name="TKRTransverseStayClear" value="372.0">Tranverse dimension of
            TKR Stay Clear envelope from LAT-DS-00038-2</prim>
    <prim name="TKRVertStayClear" value="640.0">Z dimension of
            TKR Stay Clear envelope from LAT-DS-00038-2</prim>
    <prim name= "SiThick" value= "0.41" >Si thickness</prim>
            
    <prim name="closeoutThickTotalBot0" value="36.535"> total closeout thickness bottom tray </prim>
    <prim name="closeoutThickTotalTop0" value="33.995"> total closeout thickness top tray </prim>

    <prim name="closeoutThick"    value="27.92">  closeout thickness regular tray </prim>
    <prim name="closeoutThickBot" value="20.9">   closeout thickness bottom tray </prim>
    <prim name="closeoutThickTop" value="20.9">   closeout thickness top tray </prim>
                     
    <prim name="TKRCloseoutWidth" value="5.0">Width of closeout 
            walls.  Last modified 2aug02</prim>
    <prim name="glueSiThick" value="0.15">Thickness of glue
            between Si and bias plane</prim>
    <prim name="glueCoreThick" value="0.175">Thickness of glue around
            core/closeout (2-Jul-10 value was 0.075) 
    </prim>
     <prim name="glueDefThick" value="0.100">Default glue thickness,
            when neither Si nor core is involved (15oct01)</prim>

    <prim name="convThickReg" value="0.097">Thickness of conversion 
            material in "regular" layers in mm (updated 27 nov 06)
            started at 0.105</prim>
    <prim name="convThickSup" value="0.7195">
            Was  0.7205 as of 27mov06, changed from .7195, now back
            started at 0.723
    </prim>
    <prim name= "faceThick" value= "0.200">Face sheet thickness
            for all but super-glast tray and bottom tray (as of 15oct01)</prim>
    <prim name= "faceSupThick" value= "0.290">Face sheet thickness
            for super-glast trays and bottom tray (15oct01)</prim>
    <prim name="biasPlaneThick" value="0.100">Thickness of bias
            plane (15oct01)</prim>
            <!--
    <prim name="tray0Gap" value="2.050">Gap above bottom tray
            modified 21jun03</prim>
    <prim name="trayNoCnvGap" value="2.130">Gap above non-bottom
        no-converter trays</prim>
    <prim name="traySuperGap" value="2.1305">Gap above super-glast
        trays (modified 27 Nov 06 to compensate for thinner super-glast
        conversion layer</prim>
        -->
<!--    <prim name="traySuperGap" value="2.127">Gap above super-glast
        trays</prim> -->
<!--    <prim name="trayRegGap" value="2.125">Gap above regular trays. Last
        modified 2aug02</prim> -->
        
    <prim name="trayRegGap" value="2.133">Gap above regular trays. Last
        modified 27 Nov 06 to compensate for thinner conversion layer</prim>
    <!-- add 0.041 as a test -->
    <prim name="TKRTraysTotalZ" value="627.465">Height of a tracker tower.
        (From spreadsheet, 21jun03</prim>
    
    <prim name="TKRGap0Z" value="4.5"> Height of foot between bottom of bottom tray 
       and grid </prim>

<!-- inner structure of Si -->
    <prim name="ssdGap" value="0.025">gap between Si dies within a ladder 
         (15oct01)</prim>
	<prim name="SiWaferSide" value="89.5">Length and width of Si wafer</prim>
    <prim name="SiWaferActiveSide" value="87.552">Length and width of active
         area on a wafer</prim>
<!-- widths -->           
    <prim name="faceWidth" value="360.6">X and y width of face sheet
         (15oct01)</prim>
    <prim name= "TKRElectGap" value= "4.2">Distance between wall
         and panel edge (each edge)</prim>
    <prim name="ladderGap" value="0.20">gap between ladders</prim>
    <prim name="MCMHeight" value="23.0">Height of tracker MCM boards</prim>
    <prim name="MCMThick" value="1.1">Thickness of tracker MCM
         boards</prim>
    <prim name="MCMGap" value="0.1">Gap between MCM board and closeout
         </prim>
    <prim name="TKRWallThick" value="1.5">Thickness of tracker 
            walls</prim>
    <prim name="TKRWallLength" value="371.45">Outer dimension of square
            formed by tracker walls (Z cross-section) 
            Last modified 2aug02</prim>

<!-- some new constants LSR 08-Aug-09 -->

<!-- adjustments to the density of the tungsten -->

    <prim name="Al_3lbDensity" value="0.0481" > heavy core density</prim>
    <prim name="Al_1lbDensity" value="0.016" > regular core density</prim>

    <prim name="TKR_SiDensity" value="2.33" > silicon detector density</prim>
    <prim name="WTotalMass"         value="43631" > total mass of the 192 thin W planes </prim>
    <prim name="WTotalAlloyMass"    value="99724" > total mass of the 64 thick W planes </prim>
    
    <!--
    <prim name="WDensityFactor"      value="0.99" > 
        factor by which to adjust mass of thin converters </prim>
    <prim name="WAlloyDensityFactor" value="1.002" > 
        factor by which to adjust mass of thick converters </prim>
        -->

    <prim name="MCMMass"  value="34.4"  > mass of MCM (measured) </prim>
	  <prim name="WallMass0" value="3358"> mass of TKR walls </prim>
    <prim name="TKRTapeMass" value= "212"> mass of tape on cables, 212/16 </prim>

  <prim name="c_CloseoutRegMass" value="279" > mass of regular closeout carbon </prim>
	<prim name="c_CloseoutTopMass" value="495" > mass of top closeout carbon </prim>
	<prim name="c_CloseoutBotMass" value="1014"> mass of bottom closeout carbon </prim>
	
	<prim name="closeoutRegTotalMass" value="292.1" > mass of regular closeout </prim>
	<prim name="closeoutTopTotalMass" value="643.9" > mass of top closeout </prim>
	<prim name="closeoutBotTotalMass0" value="1697.2"> mass of bottom closeout </prim>

	<prim name="TKR_glueMass"      value="20"  > mass of a glue layer </prim>
    <!-- core glue mass was originally 20 g -->
	<prim name="TKR_coreGlueMass"  value="40"  > mass of a core glue layer </prim>
	<prim name="TKR_faceRegMass"   value="49"  > mass of regular face </prim>
	<prim name="TKR_faceSupMass"   value="71"  > mass of heavy face </prim>
	<prim name="TKR_biasBoardMass" value="26.9"> mass of bias board (measured) </prim>
	<prim name="TKR_SiDotsMass"    value="1.3" > mass of non-silvered silicone dots </prim>
	<prim name="TKR_SiAgDotsMass"  value="1.5" > mass of silvered silicone dots </prim>
  <prim name="TKR_EMIMass"       value="80"  > mass of top EMI layer </prim>
    
    <prim name="TKR_NestsMass"     value="65"  > mass of top "nests" </prim>
    <prim name="TKR_BracketsMass"  value="115" > mass of top "brackets" </prim>
    <prim name="TKR_AlignHDWMass"  value="264" > alignment hardware </prim>
	
    
    <prim name="nominalDensity" value="2.0"> 
       density of composites used only as components </prim>
       
   <prim name="zero" value="0"> just a fiddle for now </prim>
   
   <!-- measured masses for verification -->
  
    <prim name="BottomTrayMassMeas"   value="2263"> measured </prim>               
    <prim name="NoConvTrayMassMeas"   value="929">  measured </prim>       
    <prim name="RegularTrayMassMeas"  value="1173"> measured </prim>  
    <prim name="SuperTrayMassMeas"    value="2634"> measured </prim>      
    <prim name="TopTrayMassMeas"      value="1480"> measured </prim> 
    <prim name="AlignmentFixtures"    value="264">  measured </prim>
    <!-- <prim name="Tape"                 value="212">  measured </prim> --> 
    <prim name="TotalTrackerMassMeas" value="525744"> measured </prim>
    
    
    <prim name="TKR_YRotation"        value="90">   </prim>
    
    <!-- New gaps: here are the distances between the closeouts, calculated -->
    
    <prim name ="TGapBotNC"  value="4.19">   </prim>
    <prim name ="TGapNCNC"   value="4.18">   </prim>
    <prim name ="TGapNCSup"  value="5.0905">   </prim>
    <prim name ="TGapSupSup" value="5.181"> </prim>
    <prim name ="TGapSupReg" value="4.471">  </prim>
    <prim name ="TGapRegReg" value="4.38">  </prim>
		
</primCategory>
